wireguard_subnets/__init__.py
wireguard_subnets/__main__.py
wireguard_subnets/parser.py
wireguard_subnets/utils.py
wireguard_subnets/wireguard_subnets.py
wireguard_subnets-1.0.2.dist-info/LICENSE
wireguard_subnets-1.0.2.dist-info/METADATA
wireguard_subnets-1.0.2.dist-info/WHEEL
wireguard_subnets-1.0.2.dist-info/entry_points.txt
wireguard_subnets-1.0.2.dist-info/top_level.txt
wireguard_subnets-1.0.2.dist-info/zip-safe
wireguard_subnets-1.0.2.dist-info/RECORD
