Metadata-Version: 2.1
Name: wireguard-subnets
Version: 1.0.2
Summary: This program performs unattended addition and removal of remote subnets accessible through its `wg` interface to a WireGuard server's routing table.
Home-page: https://github.com/fernandoenzo/wireguard-subnets
Download-URL: https://github.com/fernandoenzo/wireguard-subnets/releases
Author: Fernando Enzo Guarini
Author-email: fernandoenzo@gmail.com
Maintainer: 
Maintainer-email: 
License: AGPLv3+
Keywords: wireguard net vpn ip link ping route routing subnet
Platform: any
Classifier: Development Status :: 5 - Production/Stable
Classifier: Environment :: Console
Classifier: Intended Audience :: End Users/Desktop
Classifier: License :: OSI Approved :: GNU Affero General Public License v3 or later (AGPLv3+)
Classifier: Natural Language :: English
Classifier: Operating System :: POSIX :: Linux
Classifier: Programming Language :: Python :: 3.7
Classifier: Programming Language :: Python :: 3.8
Classifier: Programming Language :: Python :: 3.9
Classifier: Programming Language :: Python :: 3.10
Classifier: Topic :: Communications
Classifier: Topic :: Internet
Classifier: Topic :: System :: Networking
Classifier: Topic :: Utilities
Requires-Python: >=3.7
License-File: LICENSE
